LICENSE
django_hub_sdk/__init__.py
django_hub_sdk/admin.py
django_hub_sdk/apps.py
django_hub_sdk/authentication.py
django_hub_sdk/migrations/0001_initial.py
django_hub_sdk/migrations/0002_auto_20220118_1843.py
django_hub_sdk/migrations/0003_auto_20220526_1829.py
django_hub_sdk/migrations/__init__.py
django_hub_sdk/models.py
django_hub_sdk/settings.py
django_hub_sdk/tests.py
django_hub_sdk/urls.py
django_hub_sdk/views.py
django_hub_sdk-0.1.20.dist-info/LICENSE
django_hub_sdk-0.1.20.dist-info/METADATA
django_hub_sdk-0.1.20.dist-info/WHEEL
django_hub_sdk-0.1.20.dist-info/RECORD
